dash_cool_components/DashCoolComponents.py
dash_cool_components/DateTimePicker.py
dash_cool_components/FileExplorer.py
dash_cool_components/KeyedFileBrowser.py
dash_cool_components/Keywords.py
dash_cool_components/TagInput.py
dash_cool_components/__init__.py
dash_cool_components/_imports_.py
dash_cool_components/dash_cool_components.min.js
dash_cool_components/dash_cool_components.min.js.map
dash_cool_components/index.py
dash_cool_components/metadata.json
dash_cool_components/package-info.json
dash_cool_components-0.1.8.dist-info/LICENSE
dash_cool_components-0.1.8.dist-info/METADATA
dash_cool_components-0.1.8.dist-info/WHEEL
dash_cool_components-0.1.8.dist-info/top_level.txt
dash_cool_components-0.1.8.dist-info/RECORD
