Metadata-Version: 2.1
Name: dash-cool-components
Version: 0.1.8
Summary: Cool React components, wrapped for Plotly Dash
Home-page: https://github.com/Tauffer-Consulting/dash-cool-components
Author: Luiz Tauffer, Vinicius Camozzato Vaz and Raul Rosá <vinicvaz.dev@gmail.com>
License: MIT
Platform: UNKNOWN
Classifier: Framework :: Dash
Requires-Dist: dash
